{
  "doi": "10.31234/osf.io/g6hf4",
  "doi_url": "https://doi.org/10.31234/osf.io/g6hf4",
  "title": "CogNGen: Constructing the kernel of a hyperdimensional predictive processing cognitive architecture",
  "year": 2022,
  "journal": null,
  "authors": [
    "Alexander G. Ororbia",
    "M. Alex Kelly"
  ],
  "abstract": "We present a new cognitive architecture that combines two neurobiologically-plausible computational elements: (1) a variant of predictive processing known as neural generative coding (NGC) and (2) hyperdimensional / vector-symbolic models of human memory. We draw inspiration from well- known cognitive architectures such as ACT-R, Soar, Leabra, and Spaun/Nengo. Our cognitive architecture, the COGni- tive Neural GENerative system (CogNGen), is in broad agree- ment with these architectures, but provides a level of detail between ACT-R’s high-level, symbolic description of human cognition and Spaun’s low-level neurobiological description. CogNGen creates the groundwork for developing agents that learn continually from diverse tasks and model human performance at larger scales than what is possible with existent cognitive architectures. We aim to develop a cognitive archi- tecture that has the power of modern machine learning techniques while retaining long-term memory, single-trial learning, transfer-learning, planning, and other capacities associated with high-level cognition. We test CogNGen on a set of maze-learning tasks, including mazes that test short-term memory and planning, and find that the synergy between its predictive processing and vector-symbolic components allow it to master the maze tasks. Future work includes testing CogN- Gen on more tasks and exploring methods for efficiently scal- ing hyperdimensional memory models to lifetime learning.",
  "link": "https://doi.org/10.31234/osf.io/g6hf4"
}