{
  "doi": "10.1126/scidip.ade6798",
  "doi_url": "https://doi.org/10.1126/scidip.ade6798",
  "title": "Engineering Diplomacy: How AI and Human Augmentation Could Remake the Art of Foreign Relations",
  "year": "2022",
  "journal": "Science & diplomacy",
  "authors": [
    "A. Buch",
    "David M. Eagleman",
    "Logan Grosenick"
  ],
  "abstract": "Through collaborations among diplomats, scientists, and engineers, authors envision artificial intelligence (AI) paired with emerging human augmentation technologies significantly improving the bandwidth, speed, and optimality of diplomacy.",
  "link": "https://doi.org/10.1126/scidip.ade6798"
}