{
  "doi": "10.2991/978-94-6239-030-0_23",
  "doi_url": "https://doi.org/10.2991/978-94-6239-030-0_23",
  "title": "Integrative Procedure Learning",
  "year": "2014",
  "journal": "Atlantis thinking machines",
  "authors": [
    "Ben Goertzel",
    "Cassio Pennachin",
    "Nil Geisweiller"
  ],
  "abstract": "“Procedure learning”—learning step-by-step procedures for carrying out internal or external operations—is a highly critical aspect of general intelligence, and is carried out in CogPrime via a complex combination of methods.",
  "link": "https://doi.org/10.2991/978-94-6239-030-0_23"
}