{
  "doi": "10.1126/science.1099945",
  "doi_url": "https://doi.org/10.1126/science.1099945",
  "title": "Programs of the Mind",
  "year": 2004,
  "journal": "Science",
  "authors": [
    "Gary Marcus"
  ],
  "abstract": "What Is Thought? . by Eric B. Baum. MIT Press, Cambridge, MA, 2004. 492 pp. $40, £25.95. ISBN 0-262-02548-5. Approaching the problem of the mind from a computer science perspective, Baum argues for a computational explanation of though--one that sees the mind as \"a complex but compact program.\"",
  "link": "https://doi.org/10.1126/science.1099945"
}